requests_oauthlib_uma/__init__.py
requests_oauthlib_uma/exceptions.py
requests_oauthlib_uma/uma2_client.py
requests_oauthlib_uma/uma2_session.py
requests_oauthlib_uma-0.1.3.dist-info/LICENSE
requests_oauthlib_uma-0.1.3.dist-info/METADATA
requests_oauthlib_uma-0.1.3.dist-info/WHEEL
requests_oauthlib_uma-0.1.3.dist-info/RECORD
