Metadata-Version: 2.3
Name: requests-oauthlib-uma
Version: 0.1.3
Summary: UMA 2.0 session and client support for requests-oauthlib
License: MIT
Keywords: requests,oauthlib,oauth2,user-managed access,uma,uma2,uma2.0
Author: Dave Sutherland
Author-email: dave@daveography.ca
Requires-Python: >=3.9
Classifier: License :: OSI Approved :: MIT License
Classifier: Programming Language :: Python :: 3
Classifier: Programming Language :: Python :: 3.9
Classifier: Programming Language :: Python :: 3.10
Classifier: Programming Language :: Python :: 3.11
Classifier: Programming Language :: Python :: 3.12
Classifier: Programming Language :: Python :: 3.13
Requires-Dist: requests-oauthlib (>=2.0.0)
Requires-Dist: tenacity (>=9.0.0)
Requires-Dist: typing-extensions (>=4.12.2)
Project-URL: Repository, https://github.com/Daveography/requests-oauthlib-uma
